yubihsm/__init__.py
yubihsm/backends/__init__.py
yubihsm/backends/http.py
yubihsm/backends/usb.py
yubihsm/core.py
yubihsm/defs.py
yubihsm/exceptions.py
yubihsm/objects.py
yubihsm/py.typed
yubihsm/utils.py
yubihsm-3.1.1.dist-info/COPYING
yubihsm-3.1.1.dist-info/METADATA
yubihsm-3.1.1.dist-info/WHEEL
yubihsm-3.1.1.dist-info/RECORD
