Metadata-Version: 2.3
Name: yubihsm
Version: 3.1.1
Summary: Library for communication with a YubiHSM 2 over HTTP or USB.
License: Apache License
Author: Dain Nilsson
Author-email: <dain@yubico.com>
Requires-Python: >=3.9
Classifier: Operating System :: OS Independent
Classifier: Programming Language :: Python
Classifier: Development Status :: 5 - Production/Stable
Classifier: License :: OSI Approved :: Apache Software License
Classifier: Topic :: Security :: Cryptography
Classifier: Topic :: Software Development :: Libraries
Provides-Extra: http
Provides-Extra: usb
Requires-Dist: cryptography (>=2.6,<47)
Requires-Dist: pyusb (>=1.0,<2.0) ; extra == "usb"
Requires-Dist: requests (>=2.0,<3.0) ; extra == "http"
Project-URL: Homepage, https://developers.yubico.com/YubiHSM2/
Project-URL: Repository, https://github.com/Yubico/python-yubihsm
